saypy/__init__.py
saypy/__main__.py
saypy/core.py
saypy-0.0.2.dist-info/METADATA
saypy-0.0.2.dist-info/WHEEL
saypy-0.0.2.dist-info/entry_points.txt
saypy-0.0.2.dist-info/top_level.txt
saypy-0.0.2.dist-info/RECORD
