Metadata-Version: 2.1
Name: saypy
Version: 0.0.2
Summary: A very pointless, yet very friendly Python package.
Home-page: UNKNOWN
Author: Matt Eads
License: UNKNOWN
Platform: UNKNOWN
